graph_attention_student/VERSION
graph_attention_student/__init__.py
graph_attention_student/cli.py
graph_attention_student/data.py
graph_attention_student/metrics.py
graph_attention_student/testing.py
graph_attention_student/typing.py
graph_attention_student/util.py
graph_attention_student/utils.py
graph_attention_student/visualization.py
graph_attention_student/assets/models/aqsoldb/fingerprint.pb
graph_attention_student/assets/models/aqsoldb/keras_metadata.pb
graph_attention_student/assets/models/aqsoldb/process.py
graph_attention_student/assets/models/aqsoldb/saved_model.pb
graph_attention_student/assets/models/aqsoldb/variables/variables.data-00000-of-00001
graph_attention_student/assets/models/aqsoldb/variables/variables.index
graph_attention_student/examples/00_basic_usage.ipynb
graph_attention_student/examples/00_quickstart.py
graph_attention_student/examples/01_full_example.ipynb
graph_attention_student/examples/01_train_custom.py
graph_attention_student/examples/02_saving_models.py
graph_attention_student/examples/03_loading_models.py
graph_attention_student/examples/04_counterfactuals.py
graph_attention_student/examples/05_predict_smiles.py
graph_attention_student/examples/README.rst
graph_attention_student/examples/__init__.py
graph_attention_student/examples/clogp.csv
graph_attention_student/examples/model.ckpt
graph_attention_student/examples/test_clogp.csv
graph_attention_student/examples/train_clogp.csv
graph_attention_student/experiments/README.md
graph_attention_student/experiments/README.rst
graph_attention_student/experiments/analyze_ensemble.ipynb
graph_attention_student/experiments/analyze_ensemble_colors.ipynb
graph_attention_student/experiments/analyze_ex_01.ipynb
graph_attention_student/experiments/analyze_ex_02.ipynb
graph_attention_student/experiments/contrastive_clustering.ipynb
graph_attention_student/experiments/explain.ipynb
graph_attention_student/experiments/plot_explanations.py
graph_attention_student-1.0.0.dist-info/METADATA
graph_attention_student-1.0.0.dist-info/WHEEL
graph_attention_student-1.0.0.dist-info/entry_points.txt
graph_attention_student-1.0.0.dist-info/RECORD
