Metadata-Version: 2.4
Name: graph_attention_student
Version: 1.0.0
Summary: MEGAN: Multi Explanation Graph Attention Network
Author-email: Jonas Teufel <jonseb1998@gmail.com>
Maintainer-email: Jonas Teufel <jonseb1998@gmail.com>
License-Expression: MIT
Keywords: attention,chemistry,deep learning,explainable ai,graph attention,graph neural network,interpretability,machine learning,molecular property prediction,pytorch
Classifier: Development Status :: 4 - Beta
Classifier: Intended Audience :: Developers
Classifier: Intended Audience :: Science/Research
Classifier: License :: OSI Approved :: MIT License
Classifier: Operating System :: OS Independent
Classifier: Programming Language :: Python :: 3
Classifier: Programming Language :: Python :: 3.10
Classifier: Programming Language :: Python :: 3.11
Classifier: Programming Language :: Python :: 3.12
Classifier: Programming Language :: Python :: 3.13
Classifier: Topic :: Scientific/Engineering :: Artificial Intelligence
Classifier: Topic :: Scientific/Engineering :: Chemistry
Classifier: Topic :: Software Development :: Libraries :: Python Modules
Requires-Python: <3.14,>=3.8
Requires-Dist: cairosvg>=2.5.2
Requires-Dist: click>=7.1.2
Requires-Dist: hdbscan>=0.8.33
Requires-Dist: imageio>=2.19.0
Requires-Dist: jinja2>=3.0.3
Requires-Dist: lightning>=2.1.3
Requires-Dist: matplotlib>=3.5.3
Requires-Dist: nltk>=3.7
Requires-Dist: numpy<2.0.0,>=1.22.0
Requires-Dist: orjson>=3.8.0
Requires-Dist: poetry-bumpversion>=0.3.0
Requires-Dist: polars>=1.0.0
Requires-Dist: pycomex>=0.21.0
Requires-Dist: pydyf<0.11.0; python_version < '3.9'
Requires-Dist: rdkit>=2022.9.1
Requires-Dist: seaborn>=0.13.1
Requires-Dist: torch-geometric>=2.4.0
Requires-Dist: torch<2.5.1,>=2.1.2
Requires-Dist: umap-learn>=0.5.3
Requires-Dist: vgd-counterfactuals>=0.1.0
Requires-Dist: visual-graph-datasets>=0.17.0
Requires-Dist: weasyprint>=57.1
